keppy/__init__.py
keppy/channel.py
keppy/constant_register.py
keppy/device.py
keppy/project.py
keppy/register.py
keppy/regular_register.py
keppy/simulator_device.py
keppy/string_register.py
keppy/tag.py
keppy/tag_data_type.py
keppy/tag_group.py
keppy/tag_type_siemens.py
keppy-0.0.9.dist-info/METADATA
keppy-0.0.9.dist-info/WHEEL
keppy-0.0.9.dist-info/license.txt
keppy-0.0.9.dist-info/top_level.txt
keppy-0.0.9.dist-info/RECORD
