Metadata-Version: 2.1
Name: keppy
Version: 0.0.9
Summary: A Python parser of Kepware projects
Home-page: https://github.com/jmbeach/KEP.py
Author: jmbeach
Author-email: jaredbeachdesign@gmail.com
License: UNKNOWN
Keywords: kepware parser
Platform: UNKNOWN
Requires-Dist: Enum34
